crm_umkm/__init__.py
crm_umkm/server.py
crm_umkm/test.py
crm_umkm/db/__init__.py
crm_umkm/db/init.py
crm_umkm/db/models.py
crm_umkm/db/schema.py
crm_umkm/db/session.py
crm_umkm-0.1.0.dist-info/METADATA
crm_umkm-0.1.0.dist-info/WHEEL
crm_umkm-0.1.0.dist-info/entry_points.txt
crm_umkm-0.1.0.dist-info/licenses/LICENSE.md
crm_umkm-0.1.0.dist-info/RECORD
