Metadata-Version: 2.4
Name: crm-umkm
Version: 0.1.0
Summary: A Model Context Protocol (MCP) server for managing small business (UMKM) customer relationships, product sales, and order tracking using SQLite.
Author-email: Lantip <lantip@gmail.com>
License: ABRMS
License-File: LICENSE.md
Keywords: crm,llm,mcp,transaction,umkm
Classifier: Development Status :: 4 - Beta
Classifier: Intended Audience :: Developers
Classifier: License :: OSI Approved :: MIT License
Classifier: Programming Language :: Python :: 3
Classifier: Programming Language :: Python :: 3.10
Requires-Python: >=3.10
Requires-Dist: mcp>=1.4.1
Requires-Dist: pydantic>=2.0
Requires-Dist: requests>=2.31
Requires-Dist: sqlalchemy>=2.0
